pyprotoc_plugin/__init__.py
pyprotoc_plugin/helpers.py
pyprotoc_plugin/plugins.py
resemble/monkeys.py
resemble/options.py
resemble/protoc-gen-resemble_python
resemble/protoc-gen-resemble_react
resemble/protoc_gen_resemble_generic.py
resemble/protoc_gen_resemble_python.py
resemble/protoc_gen_resemble_react.py
resemble/rc.py
resemble/rsm.py
resemble/settings.py
resemble/templates/resemble.py.j2
resemble/templates/resemble_react.ts.j2
resemble/v1alpha1/options.proto
resemble/v1alpha1/options_pb2.py
resemble/v1alpha1/options_pb2_grpc.py
reboot_resemble_cli-0.6.1.dist-info/LICENSE
reboot_resemble_cli-0.6.1.dist-info/METADATA
reboot_resemble_cli-0.6.1.dist-info/WHEEL
reboot_resemble_cli-0.6.1.dist-info/entry_points.txt
reboot_resemble_cli-0.6.1.dist-info/top_level.txt
reboot_resemble_cli-0.6.1.dist-info/RECORD
