Metadata-Version: 2.1
Name: reboot-resemble-cli
Version: 0.6.1
Summary: The Resemble CLI tool
Classifier: License :: OSI Approved :: Apache Software License
Classifier: Operating System :: OS Independent
Classifier: Programming Language :: Python :: 3
Requires-Python: >=3.10
License-File: LICENSE
Requires-Dist: grpcio ==1.56.0
Requires-Dist: grpcio-reflection ==1.56.0
Requires-Dist: grpcio-status ==1.56.0
Requires-Dist: grpcio-tools ==1.56.0
Requires-Dist: protobuf ==4.21.11
Requires-Dist: kubernetes ==24.2.0
Requires-Dist: kubernetes-asyncio ==24.2.2
Requires-Dist: mypy-extensions ==0.4.3
Requires-Dist: jinja2 ==3.1.2
Requires-Dist: urllib3 ==1.26.15
Requires-Dist: colorama ==0.4.6
Requires-Dist: watchdog ==3.0.0
Requires-Dist: psutil ==5.9.5
Requires-Dist: pyprctl ==0.1.3
Requires-Dist: gitpython ==3.1.31
Requires-Dist: aiohttp ==3.8.5
Requires-Dist: packaging ==23.1
